[{"line":1,"elements":[{"start_timestamp":"2024-01-05T09:55:56.551Z","line":4,"name":"Login page","description":"","id":"verify-the-login-functionality;login-page","type":"scenario","keyword":"Scenario","steps":[{"result":{"duration":12730815400,"status":"passed"},"line":5,"name":"The user is on the home page","match":{"location":"stepDefinition.E2ETests.theUserIsOnTheHomePage()"},"keyword":"Given "},{"result":{"duration":1291800,"status":"passed"},"line":6,"name":"the user name and password is provided","match":{"location":"stepDefinition.E2ETests.theUserNameAndPasswordIsProvided()"},"keyword":"When "}],"tags":[{"name":"@Test"}]}],"name":"Verify the login functionality","description":"","id":"verify-the-login-functionality","keyword":"Feature","uri":"file:src/test/resources/Features/Loginpage.feature","tags":[]}]